async_rundeck/__init__.py
async_rundeck/client.py
async_rundeck/definitions.py
async_rundeck/exceptions.py
async_rundeck/misc.py
async_rundeck/proto/__init__.py
async_rundeck/proto/_forward_refs.py
async_rundeck/proto/definitions.py
async_rundeck/proto/execution.py
async_rundeck/proto/job.py
async_rundeck/proto/json_types.py
async_rundeck/proto/metric.py
async_rundeck/proto/project.py
async_rundeck/proto/storage.py
async_rundeck/proto/system.py
async_rundeck/proto/user.py
async_rundeck/rundeck.py
async_rundeck-0.1.7.dist-info/LICENSE
async_rundeck-0.1.7.dist-info/WHEEL
async_rundeck-0.1.7.dist-info/METADATA
async_rundeck-0.1.7.dist-info/RECORD
