Metadata-Version: 2.1
Name: async-rundeck
Version: 0.1.7
Summary: Asynchronous rundeck API client
Home-page: https://github.com/elda27/async_rundeck
Keywords: rundeck,asyncio
Author: elda27
Author-email: kaz.birdstick@gmail.com
Requires-Python: >=3.8,<4.0
Classifier: Programming Language :: Python :: 3
Classifier: Programming Language :: Python :: 3.8
Classifier: Programming Language :: Python :: 3.9
Classifier: Programming Language :: Python :: 3.10
Classifier: Programming Language :: Python :: 3.11
Requires-Dist: aiohttp (>=3.8.1,<4.0.0)
Requires-Dist: pydantic (>=1.9.0,<2.0.0)
Project-URL: Repository, https://github.com/elda27/async_rundeck
